{"url":"https://www.youtube.com/watch?v=Lly_fl0GvvQ","title":"DUKI, Ysy A, Neo Pistea - TODO NEGRO #ModoDiablo","shortTitle":"TODO NEGRO","singers":"DUKI & Ysy A & Neo Pistea","date":"2018-11-17T08:14:03Z","thumbnails":{"default":{"url":"https://i.ytimg.com/vi/Lly_fl0GvvQ/default.jpg","width":120,"height":90},"medium":{"url":"https://i.ytimg.com/vi/Lly_fl0GvvQ/mqdefault.jpg","width":320,"height":180},"high":{"url":"https://i.ytimg.com/vi/Lly_fl0GvvQ/hqdefault.jpg","width":480,"height":360},"standard":{"url":"https://i.ytimg.com/vi/Lly_fl0GvvQ/sddefault.jpg","width":640,"height":480},"maxres":{"url":"https://i.ytimg.com/vi/Lly_fl0GvvQ/maxresdefault.jpg","width":1280,"height":720}},"position":54,"videoOwnerChannelTitle":"Mododiablo Oficial"}