{"url":"https://www.youtube.com/watch?v=JofVkjnCfOY","title":"Tali Goya FT Duki - Aguacero (Video Oficial)","shortTitle":"Aguacero","singers":"Tali Goya FT Duki","date":"2021-03-16T02:02:46Z","thumbnails":{"default":{"url":"https://i.ytimg.com/vi/JofVkjnCfOY/default.jpg","width":120,"height":90},"medium":{"url":"https://i.ytimg.com/vi/JofVkjnCfOY/mqdefault.jpg","width":320,"height":180},"high":{"url":"https://i.ytimg.com/vi/JofVkjnCfOY/hqdefault.jpg","width":480,"height":360}},"position":165,"videoOwnerChannelTitle":"TaliGoyaTV"}